envoy_client/__init__.py
envoy_client/auth.py
envoy_client/client.py
envoy_client/models.py
envoy_client/transport.py
envoy_client-0.1.1.dist-info/LICENSE
envoy_client-0.1.1.dist-info/METADATA
envoy_client-0.1.1.dist-info/WHEEL
envoy_client-0.1.1.dist-info/top_level.txt
envoy_client-0.1.1.dist-info/RECORD
