Metadata-Version: 2.1
Name: envoy-client
Version: 0.1.1
Summary: 2030.5 DER Client
Home-page: https://github.com/bsgip/envoy-client
Author: BSGIP
License: UNKNOWN
Platform: UNKNOWN
Requires-Python: >=3.6
License-File: LICENSE
Requires-Dist: requests (>=2.20)
Requires-Dist: xmltodict (>=0.12)
Requires-Dist: pydantic (>=1.8)
